odoo/addons/mail_quoted_reply/README.rst
odoo/addons/mail_quoted_reply/__init__.py
odoo/addons/mail_quoted_reply/__manifest__.py
odoo/addons/mail_quoted_reply/data/reply_template.xml
odoo/addons/mail_quoted_reply/i18n/ca.po
odoo/addons/mail_quoted_reply/i18n/ca_ES.po
odoo/addons/mail_quoted_reply/i18n/es.po
odoo/addons/mail_quoted_reply/i18n/es_ES.po
odoo/addons/mail_quoted_reply/i18n/es_PA.po
odoo/addons/mail_quoted_reply/i18n/mail_quoted_reply.pot
odoo/addons/mail_quoted_reply/models/__init__.py
odoo/addons/mail_quoted_reply/models/mail_message.py
odoo/addons/mail_quoted_reply/readme/CONTRIBUTORS.rst
odoo/addons/mail_quoted_reply/readme/DESCRIPTION.rst
odoo/addons/mail_quoted_reply/readme/USAGE.rst
odoo/addons/mail_quoted_reply/static/description/icon.png
odoo/addons/mail_quoted_reply/static/description/index.html
odoo/addons/mail_quoted_reply/static/src/js/mail_message_reply.js
odoo/addons/mail_quoted_reply/static/src/xml/mail_message_reply.xml
odoo/addons/mail_quoted_reply/templates/assets.xml
odoo/addons/mail_quoted_reply/tests/__init__.py
odoo/addons/mail_quoted_reply/tests/test_reply.py
odoo/addons/mail_quoted_reply/wizards/__init__.py
odoo/addons/mail_quoted_reply/wizards/mail_compose_message_reply.py
odoo13_addon_mail_quoted_reply-13.0.1.0.1.dev11.dist-info/METADATA
odoo13_addon_mail_quoted_reply-13.0.1.0.1.dev11.dist-info/WHEEL
odoo13_addon_mail_quoted_reply-13.0.1.0.1.dev11.dist-info/top_level.txt
odoo13_addon_mail_quoted_reply-13.0.1.0.1.dev11.dist-info/RECORD
